{
	"id": "transition_started",
	"title": {
		"en": "Transition is started",
		"nl": "Transitie is gestart",
		"de": "Übergang ist gestartet"
	},
	"titleFormatted": {
		"en": "Transition [[name]] is started",
		"nl": "Transitie [[name]] is gestart",
		"de": "Übergang [[name]] ist gestartet"
	},
	"hint": {
		"en": "This card is activated when a transition with the provided name is started.",
		"nl": "Dit kaartje wordt geactiveerd als een transitie met de ingevoerde naam is gestart.",
		"de": "Diese Karte wird aktiviert wenn ein Übergang mit dem angegebenen Namen gestartet ist."
	},
	"args": [
		{
			"name": "name",
			"title": {
				"en": "Name",
				"nl": "Naam",
				"de": "Name"
			},
			"type": "text"
		}
	],
	"tokens": [
		{
			"name": "name",
			"type": "string",
			"title": {
				"en": "Name",
				"nl": "Naam",
				"de": "Name"
			},
			"example": {
				"en": "bathroom",
				"nl": "badkamer",
				"de": "Badezimmer"
			}
		},
		{
			"name": "seconds",
			"type": "number",
			"title": {
				"en": "Duration (s)",
				"nl": "Looptijd (s)",
				"de": "Dauer (s)"
			},
			"example": 60
		}
	]
}
